anity/__init__.py
anity/__main__.py
anity-0.1.0.dist-info/METADATA
anity-0.1.0.dist-info/WHEEL
anity-0.1.0.dist-info/entry_points.txt
anity-0.1.0.dist-info/top_level.txt
anity-0.1.0.dist-info/RECORD
