Metadata-Version: 2.1
Name: anity
Version: 0.1.0
Summary: Deploy monitor test suites in anity.io
Home-page: https://anity.io
Author: Anity
Author-email: info@anity.io
License: MIT
Platform: UNKNOWN
Classifier: License :: OSI Approved :: MIT License
Classifier: Programming Language :: Python :: 3
Classifier: Programming Language :: Python :: 3.9
Requires-Dist: Click
Requires-Dist: requests
